tests/__init__.py
tests/test_constructor.py
tests/test_plot.py
tests/test_trees.py
tests/test_util.py
wkskel/__init__.py
wkskel/skeleton.py
wkskel/types.py
wkskel-0.0.2.dist-info/LICENSE
wkskel-0.0.2.dist-info/METADATA
wkskel-0.0.2.dist-info/WHEEL
wkskel-0.0.2.dist-info/top_level.txt
wkskel-0.0.2.dist-info/RECORD
